version_stamp/__init__.py
version_stamp/stamp_utils.py
version_stamp/version.py
version_stamp/vmn.py
vmn-0.8.11.dist-info/LICENSE.txt
vmn-0.8.11.dist-info/METADATA
vmn-0.8.11.dist-info/WHEEL
vmn-0.8.11.dist-info/entry_points.txt
vmn-0.8.11.dist-info/top_level.txt
vmn-0.8.11.dist-info/RECORD
