Metadata-Version: 2.1
Name: vmn
Version: 0.8.11
Summary: Stamping utility
Home-page: https://github.com/final-israel/vmn
Author: Pavel Rogovoy
Author-email: pavelr@final.israel
License: GPL-3.0-only
Requires-Python: >=3.6.0
License-File: LICENSE.txt
Requires-Dist: filelock >=3.2.0
Requires-Dist: GitPython ==3.1.18
Requires-Dist: packaging >=21.0
Requires-Dist: PyYAML >=5.4.1
Requires-Dist: tomlkit >0.7.2
Requires-Dist: Jinja2 >=3.0.3
